acemeta/Console.py
acemeta/Discord.py
acemeta/Files.py
acemeta/GitHub.py
acemeta/Minecraft.py
acemeta/Numbers.py
acemeta/Stochastics.py
acemeta/__init__.py
acemeta-0.2.7.dist-info/METADATA
acemeta-0.2.7.dist-info/WHEEL
acemeta-0.2.7.dist-info/top_level.txt
acemeta-0.2.7.dist-info/RECORD
