Metadata-Version: 2.1
Name: acemeta
Version: 0.2.7
Summary: Library for typical workflows
Author: Annhilati
Requires-Dist: requests
